{
  "intro": "MEET \nOUR \nTEAM",
  "intro2": "Get to know us \nmuch better",
  "members": [
    {
      "order": 1,
      "info": {
        "name": "Mark Stone",
        "position": "CEO"
      }
    },
    {
      "order": 2,
      "info": {
        "name": "Kate Stonehold",
        "position": "DESIGNER"
      }
    },
    {
      "order": 3,
      "info": {
        "name": "Terry Jackobs",
        "position": "CODER"
      }
    },
    {
      "order": 4,
      "info": {
        "name": "Jane Perry",
        "position": "HR"
      }
    },
    {
      "order": 5,
      "info": {
        "name": "Peter Williams",
        "position": "DESIGNER"
      }
    },
    {
      "order": 6,
      "info": {
        "name": "John Doe",
        "position": "MARKETING"
      }
    }
  ]
}
